ai_comm/__init__.py
ai_comm/cli.py
ai_comm/kitten_client.py
ai_comm/polling.py
ai_comm/registry.py
ai_comm/adapters/__init__.py
ai_comm/adapters/aider.py
ai_comm/adapters/base.py
ai_comm/adapters/claude.py
ai_comm/adapters/codex.py
ai_comm/adapters/cursor.py
ai_comm/adapters/gemini.py
ai_comm/adapters/generic.py
ai_comm/adapters/opencode.py
ai_comm/commands/__init__.py
ai_comm/commands/response.py
ai_comm/commands/send.py
ai_comm/commands/window.py
ai_comm/kitten/ai_comm_kitten.py
ai_comm/parsers/__init__.py
ai_comm/parsers/base.py
ai_comm/parsers/utils.py
ai_comm/services/__init__.py
ai_comm/services/interaction.py
ai_comm-0.2.11.dist-info/METADATA
ai_comm-0.2.11.dist-info/WHEEL
ai_comm-0.2.11.dist-info/entry_points.txt
ai_comm-0.2.11.dist-info/licenses/LICENSE
ai_comm-0.2.11.dist-info/RECORD
