Metadata-Version: 2.4
Name: ai-comm
Version: 0.2.11
Summary: Cross-AI CLI communication tool for kitty terminal
Project-URL: Homepage, https://github.com/a322655/ai-comm
Project-URL: Repository, https://github.com/a322655/ai-comm
Author: WindFade
License-Expression: MIT
License-File: LICENSE
Keywords: ai,cli,communication,kitty,terminal
Classifier: Development Status :: 4 - Beta
Classifier: Environment :: Console
Classifier: Intended Audience :: Developers
Classifier: License :: OSI Approved :: MIT License
Classifier: Programming Language :: Python :: 3.11
Classifier: Programming Language :: Python :: 3.12
Classifier: Programming Language :: Python :: 3.13
Classifier: Topic :: Utilities
Requires-Python: >=3.11
Requires-Dist: typer>=0.15.0
Requires-Dist: wcwidth>=0.2
